envzigzag.py
envzigzag-0.1.dist-info/entry_points.txt
envzigzag-0.1.dist-info/WHEEL
envzigzag-0.1.dist-info/METADATA
envzigzag-0.1.dist-info/RECORD
