Metadata-Version: 1.2
Name: envzigzag
Version: 0.1
Summary: Compare environment variables in the terminal.
Home-page: https://gitlab.com/takluyver/envzigzag
License: UNKNOWN
Author: Thomas Kluyver
Author-email: thomas@kluyver.me.uk
Requires-Python: >=3.5
Classifier: License :: OSI Approved :: MIT License
Classifier: Environment :: Console
